irtcamera/__init__.py
irtcamera/mlx90640.py
irtcamera/__pycache__/__init__.cpython-39.pyc
irtcamera/__pycache__/mlx90640.cpython-39.pyc
irt_camera-0.0.1a1.dist-info/LICENSE
irt_camera-0.0.1a1.dist-info/METADATA
irt_camera-0.0.1a1.dist-info/WHEEL
irt_camera-0.0.1a1.dist-info/top_level.txt
irt_camera-0.0.1a1.dist-info/RECORD
